README.rst
setup.py
tornpg.py
tornpg.egg-info/PKG-INFO
tornpg.egg-info/SOURCES.txt
tornpg.egg-info/dependency_links.txt
tornpg.egg-info/requires.txt
tornpg.egg-info/top_level.txt