Metadata-Version: 1.0
Name: tornpg
Version: 0.1.0
Summary: A lightweight PostgresSQL database adapter wrappered around psycopg2.
Home-page: https://github.com/markgao/tornpg
Author: Mark Gao
Author-email: gx@stoneopus.com
License: http://www.apache.org/licenses/LICENSE-2.0
Platform: UNKNOWN
